<?xml version="1.0"?>
<!DOCTYPE hibernate-mapping PUBLIC "-//Hibernate/Hibernate Mapping DTD 3.0//EN"
"http://www.hibernate.org/dtd/hibernate-mapping-3.0.dtd">
<!-- Generated 19-feb-2020 19:59:25 by Hibernate Tools 4.3.1 -->
<hibernate-mapping>
    <class name="POJOS.Estacion" table="estacion" catalog="es_autobus" optimistic-lock="version">
        <id name="id" type="java.lang.Integer">
            <column name="id" />
            <generator class="identity" />
        </id>
        <property name="nombre" type="string">
            <column name="nombre" length="50" not-null="true" />
        </property>
        <property name="direccion" type="string">
            <column name="direccion" length="50" not-null="true" />
        </property>
        <property name="localidad" type="string">
            <column name="localidad" length="50" not-null="true" />
        </property>
        <set name="rutasForIdDestino" table="ruta" inverse="true" lazy="true" fetch="select">
            <key>
                <column name="id_destino" not-null="true" />
            </key>
            <one-to-many class="POJOS.Ruta" />
        </set>
        <set name="rutasForIdOrigen" table="ruta" inverse="true" lazy="true" fetch="select">
            <key>
                <column name="id_origen" not-null="true" />
            </key>
            <one-to-many class="POJOS.Ruta" />
        </set>
    </class>
</hibernate-mapping>
